hashformers/__init__.py
hashformers/beamsearch/__init__.py
hashformers/beamsearch/algorithm.py
hashformers/beamsearch/bert_lm.py
hashformers/beamsearch/data_structures.py
hashformers/beamsearch/gpt2_lm.py
hashformers/beamsearch/minicons_lm.py
hashformers/beamsearch/model_lm.py
hashformers/beamsearch/reranker.py
hashformers/ensemble/__init__.py
hashformers/ensemble/top2_fusion.py
hashformers/evaluation/__init__.py
hashformers/evaluation/modeler.py
hashformers/evaluation/utils.py
hashformers/experiments/__init__.py
hashformers/experiments/evaluation.py
hashformers/experiments/utils.py
hashformers/segmenter/__init__.py
hashformers/segmenter/auto.py
hashformers/segmenter/base_segmenter.py
hashformers/segmenter/data_structures.py
hashformers/segmenter/regex_segmenter.py
hashformers/segmenter/segmenter.py
hashformers/spacy/__init__.py
hashformers-2.2.0.dist-info/licenses/LICENSE
hashformers-2.2.0.dist-info/METADATA
hashformers-2.2.0.dist-info/WHEEL
hashformers-2.2.0.dist-info/top_level.txt
hashformers-2.2.0.dist-info/RECORD
