Metadata-Version: 2.4
Name: hashformers
Version: 2.2.0
Summary: Word segmentation with transformers
Home-page: https://github.com/ruanchaves/hashformers
Author: Ruan Chaves Rodrigues
Author-email: ruanchave93@gmail.com
Keywords: word-segmentation hashtag nlp transformers spacy
Classifier: Development Status :: 4 - Beta
Classifier: Intended Audience :: Developers
Classifier: Intended Audience :: Science/Research
Classifier: License :: OSI Approved :: MIT License
Classifier: Programming Language :: Python :: 3
Classifier: Programming Language :: Python :: 3.8
Classifier: Programming Language :: Python :: 3.9
Classifier: Programming Language :: Python :: 3.10
Classifier: Programming Language :: Python :: 3.11
Classifier: Topic :: Scientific/Engineering :: Artificial Intelligence
Classifier: Topic :: Text Processing :: Linguistic
Requires-Python: >=3.8
License-File: LICENSE
Requires-Dist: minicons
Requires-Dist: twitter-text-python
Requires-Dist: pandas
Provides-Extra: spacy
Requires-Dist: spacy>=3.0.0; extra == "spacy"
Dynamic: author
Dynamic: author-email
Dynamic: classifier
Dynamic: description
Dynamic: description-content-type
Dynamic: home-page
Dynamic: keywords
Dynamic: license-file
Dynamic: provides-extra
Dynamic: requires-dist
Dynamic: requires-python
Dynamic: summary
